blakbox/__init__.py
blakbox/atom.py
blakbox/globs.py
blakbox/quotes.py
blakbox/util.py
blakbox/version.py
blakbox/app/__init__.py
blakbox/app/app.py
blakbox/app/scene.py
blakbox/app/resource/__init__.py
blakbox/app/resource/camera.py
blakbox/app/resource/clock.py
blakbox/app/resource/events.py
blakbox/app/resource/inputs.py
blakbox/app/resource/manager.py
blakbox/app/resource/object.py
blakbox/app/resource/objectgrid.py
blakbox/app/resource/particle.py
blakbox/app/resource/renderer.py
blakbox/app/resource/surface.py
blakbox/app/resource/surfarray.py
blakbox/app/resource/surfatlas.py
blakbox/app/resource/tilemap.py
blakbox/app/resource/window.py
blakbox/app/ui/__init__.py
blakbox/app/ui/element.py
blakbox/app/ui/interface.py
blakbox/app/ui/textbox.py
blakbox/assets/fonts/megamax.ttf
blakbox/assets/fonts/slkscr.ttf
blakbox/assets/images/logo-5x.gif
blakbox/assets/images/logo-5x.png
blakbox/assets/images/logo-anim.png
blakbox/assets/images/logo.ico
blakbox/net/__init__.py
blakbox-2025.0.1.dist-info/licenses/LICENSE
blakbox-2025.0.1.dist-info/METADATA
blakbox-2025.0.1.dist-info/WHEEL
blakbox-2025.0.1.dist-info/top_level.txt
blakbox-2025.0.1.dist-info/RECORD
