Metadata-Version: 2.4
Name: BLAKBOX
Version: 2025.0.1
Summary: Reach Inside The Box...
Home-page: https://github.com/r3shape/BLAKBOX
Author: Izaiyah Stokes
Author-email: d34d0s.dev@gmail.com
Classifier: Programming Language :: Python :: 3.12
Classifier: Operating System :: OS Independent
License-File: LICENSE
Requires-Dist: pygame-ce
Dynamic: author
Dynamic: author-email
Dynamic: classifier
Dynamic: description
Dynamic: description-content-type
Dynamic: home-page
Dynamic: license-file
Dynamic: requires-dist
Dynamic: summary
